LICENSE
README.md
setup.py
pypi_scraper/__init__.py
tradingview_search_scraper.egg-info/PKG-INFO
tradingview_search_scraper.egg-info/SOURCES.txt
tradingview_search_scraper.egg-info/dependency_links.txt
tradingview_search_scraper.egg-info/requires.txt
tradingview_search_scraper.egg-info/top_level.txt